xlink/__init__.py
xlink/common/__init__.py
xlink/common/protocol.py
xlink/common/schedule_center.py
xlink/common/tools.py
xlink/master/__init__.py
xlink/master/db_config_sample.py
xlink/master/master_api.py
xlink/master/master_manager.py
xlink/master/master_server.py
xlink/master/source/__init__.py
xlink/master/source/db.py
xlink/master/source/schedule_loader.py
xlink/master/source/schedule_orm.py
xlink/master/source/schedule_repository.py
xlink/slave/__init__.py
xlink/slave/register_manager.py
xlink/slave/slave_client.py
xlink/slave/slave_service.py
xlink-0.0.13.dist-info/LICENSE
xlink-0.0.13.dist-info/METADATA
xlink-0.0.13.dist-info/WHEEL
xlink-0.0.13.dist-info/top_level.txt
xlink-0.0.13.dist-info/RECORD
