Metadata-Version: 2.1
Name: xlink
Version: 0.0.13
Summary: A package for xlink server and client.
Home-page: https://gitee.com
Author: ZQX
Author-email: 262293446@qq.com
Classifier: Programming Language :: Python :: 3
Classifier: License :: OSI Approved :: MIT License
Classifier: Operating System :: OS Independent
License-File: LICENSE
